LICENSE
MANIFEST.in
README.rst
example1.jpg
example2.png
example3.png
pypi.rst
setup.py
mplapp/__init__.py
mplapp/base.py
mplapp/button.py
mplapp/combo_box.py
mplapp/horizontal_box.py
mplapp/label.py
mplapp/line_edit.py
mplapp/plot.py
mplapp/slider.py
mplapp/spacer.py
mplapp/vertical_box.py
mplapp/window.py
mplapp.egg-info/PKG-INFO
mplapp.egg-info/SOURCES.txt
mplapp.egg-info/dependency_links.txt
mplapp.egg-info/requires.txt
mplapp.egg-info/top_level.txt