Metadata-Version: 1.1
Name: mplapp
Version: 0.1
Summary: An GUI toolkit for creating interactive applications with a set of GUI neutral
